navicat_mikimo/__init__.py
navicat_mikimo/__main__.py
navicat_mikimo/helper.py
navicat_mikimo/kinetic_solver.py
navicat_mikimo/km_k_volcanic.py
navicat_mikimo/km_volcanic.py
navicat_mikimo/plot_function.py
navicat_mikimo/replot.py
navicat_mikimo/screen_reaction_condition.py
navicat_mikimo/test_module.py
navicat_mikimo-1.0.1.dist-info/METADATA
navicat_mikimo-1.0.1.dist-info/WHEEL
navicat_mikimo-1.0.1.dist-info/entry_points.txt
navicat_mikimo-1.0.1.dist-info/top_level.txt
navicat_mikimo-1.0.1.dist-info/RECORD
