Metadata-Version: 2.1
Name: navicat_mikimo
Version: 1.0.1
Summary: microkinetic modeling code for homogeneous catalytic reactions
Home-page: https://github.com/lcmd-epfl/mikimo
Author: pregabalin_hoshiyomi
Author-email: pregabalin_Hoshiyomi <thanapat.worakul@epfl.ch>
Keywords: computational chemistry utility
Classifier: Programming Language :: Python :: 3
Classifier: Operating System :: OS Independent
Requires-Python: >=3.9
Requires-Dist: numpy >=1.24.1
Requires-Dist: scipy >=1.10.0
Requires-Dist: autograd >=1.5
Requires-Dist: matplotlib >=3.6.3
Requires-Dist: pandas >=1.5.3
Requires-Dist: h5py >=3.8.0
Requires-Dist: fire >=0.5.0
Requires-Dist: setuptools >=67.1.0
Requires-Dist: navicat-volcanic >=1.2.12
Requires-Dist: openpyxl >=3.1.2
Requires-Dist: tqdm >=4.5
